<?xml version="1.0" encoding="UTF-8" standalone="yes"?>
<p:sldLayout xmlns:a="http://schemas.openxmlformats.org/drawingml/2006/main" xmlns:r="http://schemas.openxmlformats.org/officeDocument/2006/relationships" xmlns:p="http://schemas.openxmlformats.org/presentationml/2006/main" preserve="1" userDrawn="1"><p:cSld name="Single Author"><p:spTree><p:nvGrpSpPr><p:cNvPr id="1" name=""/><p:cNvGrpSpPr/><p:nvPr/></p:nvGrpSpPr><p:grpSpPr><a:xfrm><a:off x="0" y="0"/><a:ext cx="0" cy="0"/><a:chOff x="0" y="0"/><a:chExt cx="0" cy="0"/></a:xfrm></p:grpSpPr><p:sp><p:nvSpPr><p:cNvPr id="3" name="Slide Number Placeholder 2"><a:extLst><a:ext uri="{FF2B5EF4-FFF2-40B4-BE49-F238E27FC236}"><a16:creationId xmlns:a16="http://schemas.microsoft.com/office/drawing/2014/main" id="{F5BE700C-9B65-48D2-B989-340A545D1AF8}"/></a:ext></a:extLst></p:cNvPr><p:cNvSpPr><a:spLocks noGrp="1"/></p:cNvSpPr><p:nvPr><p:ph type="sldNum" sz="quarter" idx="10"/></p:nvPr></p:nvSpPr><p:spPr/><p:txBody><a:bodyPr/><a:lstStyle/><a:p><a:fld id="{5CFA18E4-D58E-4B28-B105-28D9665A8EBC}" type="slidenum"><a:rPr lang="en-US" smtClean="0"/><a:pPr/><a:t>‹#›</a:t></a:fld><a:endParaRPr lang="en-US"/></a:p></p:txBody></p:sp><p:sp><p:nvSpPr><p:cNvPr id="4" name="Title 1"><a:extLst><a:ext uri="{FF2B5EF4-FFF2-40B4-BE49-F238E27FC236}"><a16:creationId xmlns:a16="http://schemas.microsoft.com/office/drawing/2014/main" id="{2138754E-07B4-4557-9122-37777C75797C}"/></a:ext></a:extLst></p:cNvPr><p:cNvSpPr><a:spLocks noGrp="1"/></p:cNvSpPr><p:nvPr><p:ph type="title" hasCustomPrompt="1"/></p:nvPr></p:nvSpPr><p:spPr><a:xfrm><a:off x="567039" y="342900"/><a:ext cx="11062709" cy="826183"/></a:xfrm></p:spPr><p:txBody><a:bodyPr/><a:lstStyle><a:lvl1pPr><a:defRPr lang="en-US" sz="2400" kern="1200" dirty="0"><a:solidFill><a:schemeClr val="tx1"/></a:solidFill><a:latin typeface="+mj-lt"/><a:ea typeface="+mj-ea"/><a:cs typeface="+mj-cs"/></a:defRPr></a:lvl1pPr></a:lstStyle><a:p><a:r><a:rPr lang="en-US"/><a:t>[Presenter/Moderator/Panelist] – select a title</a:t></a:r></a:p></p:txBody></p:sp><p:sp><p:nvSpPr><p:cNvPr id="10" name="Picture Placeholder 17"><a:extLst><a:ext uri="{FF2B5EF4-FFF2-40B4-BE49-F238E27FC236}"><a16:creationId xmlns:a16="http://schemas.microsoft.com/office/drawing/2014/main" id="{D96010C1-4595-4367-B9F6-DB15F9269834}"/></a:ext></a:extLst></p:cNvPr><p:cNvSpPr><a:spLocks noGrp="1"/></p:cNvSpPr><p:nvPr><p:ph type="pic" sz="quarter" idx="23" hasCustomPrompt="1"/></p:nvPr></p:nvSpPr><p:spPr><a:xfrm><a:off x="569373" y="1903422"/><a:ext cx="2194560" cy="2194560"/></a:xfrm><a:prstGeom prst="ellipse"><a:avLst/></a:prstGeom><a:pattFill prst="pct5"><a:fgClr><a:schemeClr val="accent1"/></a:fgClr><a:bgClr><a:schemeClr val="bg1"/></a:bgClr></a:pattFill><a:ln w="38100"><a:solidFill><a:schemeClr val="accent5"/></a:solidFill></a:ln></p:spPr><p:txBody><a:bodyPr anchor="ctr"/><a:lstStyle><a:lvl1pPr marL="0" indent="0" algn="ctr"><a:buNone/><a:defRPr b="1"/></a:lvl1pPr></a:lstStyle><a:p><a:r><a:rPr lang="en-US"/><a:t>Click to add portrait photo or remove</a:t></a:r></a:p></p:txBody></p:sp><p:sp><p:nvSpPr><p:cNvPr id="9" name="Text Placeholder 6"><a:extLst><a:ext uri="{FF2B5EF4-FFF2-40B4-BE49-F238E27FC236}"><a16:creationId xmlns:a16="http://schemas.microsoft.com/office/drawing/2014/main" id="{458F1CB7-C380-4D98-8B57-644A777302F2}"/></a:ext></a:extLst></p:cNvPr><p:cNvSpPr><a:spLocks noGrp="1"/></p:cNvSpPr><p:nvPr><p:ph type="body" sz="quarter" idx="24" hasCustomPrompt="1"/></p:nvPr></p:nvSpPr><p:spPr><a:xfrm><a:off x="3136392" y="1903413"/><a:ext cx="8493356" cy="2187575"/></a:xfrm><a:prstGeom prst="rect"><a:avLst/></a:prstGeom></p:spPr><p:txBody><a:bodyPr anchor="ctr"/><a:lstStyle><a:lvl1pPr marL="0" indent="0"><a:lnSpc><a:spcPct val="100000"/></a:lnSpc><a:spcBef><a:spcPts val="0"/></a:spcBef><a:spcAft><a:spcPts val="600"/></a:spcAft><a:buFontTx/><a:buNone/><a:defRPr/></a:lvl1pPr><a:lvl2pPr marL="183764" indent="0"><a:buFontTx/><a:buNone/><a:defRPr/></a:lvl2pPr><a:lvl3pPr marL="397056" indent="0"><a:buFontTx/><a:buNone/><a:defRPr/></a:lvl3pPr><a:lvl4pPr marL="566913" indent="0"><a:buFontTx/><a:buNone/><a:defRPr/></a:lvl4pPr><a:lvl5pPr marL="740645" indent="0"><a:buFontTx/><a:buNone/><a:defRPr/></a:lvl5pPr></a:lstStyle><a:p><a:pPr lvl="0"/><a:r><a:rPr lang="en-US"/><a:t>Copy and paste the first paragraph of your bio here</a:t></a:r></a:p></p:txBody></p:sp><p:sp><p:nvSpPr><p:cNvPr id="5" name="Text Placeholder 7"><a:extLst><a:ext uri="{FF2B5EF4-FFF2-40B4-BE49-F238E27FC236}"><a16:creationId xmlns:a16="http://schemas.microsoft.com/office/drawing/2014/main" id="{2BFEA3C9-368E-4564-8216-477D103F8884}"/></a:ext></a:extLst></p:cNvPr><p:cNvSpPr><a:spLocks noGrp="1"/></p:cNvSpPr><p:nvPr><p:ph type="body" sz="quarter" idx="13" hasCustomPrompt="1"/></p:nvPr></p:nvSpPr><p:spPr><a:xfrm><a:off x="574912" y="4258763"/><a:ext cx="5512296" cy="332160"/></a:xfrm><a:prstGeom prst="rect"><a:avLst/></a:prstGeom></p:spPr><p:txBody><a:bodyPr anchor="ctr"><a:noAutofit/></a:bodyPr><a:lstStyle><a:lvl1pPr marL="0" indent="0"><a:spcBef><a:spcPts val="0"/></a:spcBef><a:spcAft><a:spcPts val="0"/></a:spcAft><a:buNone/><a:defRPr sz="1800" b="0"><a:solidFill><a:schemeClr val="tx1"/></a:solidFill></a:defRPr></a:lvl1pPr><a:lvl2pPr marL="169858" indent="0"><a:buNone/><a:defRPr/></a:lvl2pPr></a:lstStyle><a:p><a:pPr lvl="0"/><a:r><a:rPr lang="en-US"/><a:t>Click to add name</a:t></a:r></a:p></p:txBody></p:sp><p:sp><p:nvSpPr><p:cNvPr id="6" name="Text Placeholder 7"><a:extLst><a:ext uri="{FF2B5EF4-FFF2-40B4-BE49-F238E27FC236}"><a16:creationId xmlns:a16="http://schemas.microsoft.com/office/drawing/2014/main" id="{4A29EB88-5E45-4FD8-93B5-97649F1F7C7B}"/></a:ext></a:extLst></p:cNvPr><p:cNvSpPr><a:spLocks noGrp="1"/></p:cNvSpPr><p:nvPr><p:ph type="body" sz="quarter" idx="14" hasCustomPrompt="1"/></p:nvPr></p:nvSpPr><p:spPr><a:xfrm><a:off x="574912" y="4656700"/><a:ext cx="5515344" cy="392985"/></a:xfrm><a:prstGeom prst="rect"><a:avLst/></a:prstGeom></p:spPr><p:txBody><a:bodyPr anchor="t"><a:noAutofit/></a:bodyPr><a:lstStyle><a:lvl1pPr marL="0" indent="0"><a:spcBef><a:spcPts val="0"/></a:spcBef><a:spcAft><a:spcPts val="0"/></a:spcAft><a:buNone/><a:defRPr sz="1400" b="0" i="0"/></a:lvl1pPr><a:lvl2pPr marL="169858" indent="0"><a:buNone/><a:defRPr/></a:lvl2pPr></a:lstStyle><a:p><a:pPr lvl="0"/><a:r><a:rPr lang="en-US"/><a:t>Click to add title and company</a:t></a:r></a:p></p:txBody></p:sp><p:sp><p:nvSpPr><p:cNvPr id="7" name="Text Placeholder 7"><a:extLst><a:ext uri="{FF2B5EF4-FFF2-40B4-BE49-F238E27FC236}"><a16:creationId xmlns:a16="http://schemas.microsoft.com/office/drawing/2014/main" id="{B7A4A313-FD4C-48FC-8393-47C4FDF1DEB7}"/></a:ext></a:extLst></p:cNvPr><p:cNvSpPr><a:spLocks noGrp="1"/></p:cNvSpPr><p:nvPr><p:ph type="body" sz="quarter" idx="15" hasCustomPrompt="1"/></p:nvPr></p:nvSpPr><p:spPr><a:xfrm><a:off x="583704" y="5118885"/><a:ext cx="5512296" cy="332160"/></a:xfrm><a:prstGeom prst="rect"><a:avLst/></a:prstGeom></p:spPr><p:txBody><a:bodyPr anchor="ctr"><a:noAutofit/></a:bodyPr><a:lstStyle><a:lvl1pPr marL="0" indent="0"><a:buNone/><a:defRPr sz="1400" b="0"/></a:lvl1pPr><a:lvl2pPr marL="169858" indent="0"><a:buNone/><a:defRPr/></a:lvl2pPr></a:lstStyle><a:p><a:r><a:rPr lang="en-US"/><a:t>Click to add email</a:t></a:r></a:p></p:txBody></p:sp></p:spTree><p:extLst><p:ext uri="{BB962C8B-B14F-4D97-AF65-F5344CB8AC3E}"><p14:creationId xmlns:p14="http://schemas.microsoft.com/office/powerpoint/2010/main" val="3019557955"/></p:ext></p:extLst></p:cSld><p:clrMapOvr><a:masterClrMapping/></p:clrMapOvr></p:sldLayout>